{
	"classtype": "kTask",
	"omnisversion": "11.0",
	"omnisbuild": 110035659,
	"internalversion": 7,
	"tvardefs": [

	],
	"cvardefs": [

	],
	"ivardefs": [

	],
	"properties": {
		"canremotedebugwhenlocked": false,
		"collectperformancedata": false,
		"componenticon": 0,
		"componentinfo": {

		},
		"componenttype": "kCompStoreHidden",
		"createdate": "2018-10-08 11:59:33",
		"desc": "",
		"editor": "",
		"editordata": "",
		"external": false,
		"issupercomponent": false,
		"moddate": "2023-10-16 06:30:20",
		"showascheckedout": false,
		"userinfo": "",
		"vcsrevision": 0,
		"version": ""
	}
}
